.gitignore
setup.py
.idea/dchilero.iml
.idea/encodings.xml
.idea/misc.xml
.idea/modules.xml
.idea/workspace.xml
dchilero/__init__.py
dchilero/cli.py
dchilero.egg-info/PKG-INFO
dchilero.egg-info/SOURCES.txt
dchilero.egg-info/dependency_links.txt
dchilero.egg-info/entry_points.txt
dchilero.egg-info/not-zip-safe
dchilero.egg-info/top_level.txt