Metadata-Version: 1.0
Name: dchilero
Version: 0.3
Summary: command line for chilero micro framework
Home-page: https://keller_matta@bitbucket.org/keller_matta/dchilero.git
Author: Keller Obdulio Matta Calderón
Author-email: kellermaca@gmail.com
License: MIT
Platform: UNKNOWN
